JianZhiOfferZhuanxiangTujiBanQuanjieDoocsKaiyuanShequ/README.md
JianZhiOfferZhuanxiangTujiBanQuanjieDoocsKaiyuanShequ/__init__.py
JianZhiOfferZhuanxiangTujiBanQuanjieDoocsKaiyuanShequ/__main__.py
JianZhiOfferZhuanxiangTujiBanQuanjieDoocsKaiyuanShequ/file.epub
JianZhiOfferZhuanxiangTujiBanQuanjieDoocsKaiyuanShequ/index.html
JianZhiOfferZhuanxiangTujiBanQuanjieDoocsKaiyuanShequ/css/__init__.py
JianZhiOfferZhuanxiangTujiBanQuanjieDoocsKaiyuanShequ/css/annotations.css
JianZhiOfferZhuanxiangTujiBanQuanjieDoocsKaiyuanShequ/css/main.css
JianZhiOfferZhuanxiangTujiBanQuanjieDoocsKaiyuanShequ/css/normalize.css
JianZhiOfferZhuanxiangTujiBanQuanjieDoocsKaiyuanShequ/css/popup.css
JianZhiOfferZhuanxiangTujiBanQuanjieDoocsKaiyuanShequ/font/__init__.py
JianZhiOfferZhuanxiangTujiBanQuanjieDoocsKaiyuanShequ/font/fontello.eot
JianZhiOfferZhuanxiangTujiBanQuanjieDoocsKaiyuanShequ/font/fontello.svg
JianZhiOfferZhuanxiangTujiBanQuanjieDoocsKaiyuanShequ/font/fontello.ttf
JianZhiOfferZhuanxiangTujiBanQuanjieDoocsKaiyuanShequ/font/fontello.woff
JianZhiOfferZhuanxiangTujiBanQuanjieDoocsKaiyuanShequ/img/__init__.py
JianZhiOfferZhuanxiangTujiBanQuanjieDoocsKaiyuanShequ/img/annotator-glyph-sprite.png
JianZhiOfferZhuanxiangTujiBanQuanjieDoocsKaiyuanShequ/img/annotator-icon-sprite.png
JianZhiOfferZhuanxiangTujiBanQuanjieDoocsKaiyuanShequ/img/apple-touch-icon.png
JianZhiOfferZhuanxiangTujiBanQuanjieDoocsKaiyuanShequ/img/cancelfullscreen.png
JianZhiOfferZhuanxiangTujiBanQuanjieDoocsKaiyuanShequ/img/close.png
JianZhiOfferZhuanxiangTujiBanQuanjieDoocsKaiyuanShequ/img/fullscreen.png
JianZhiOfferZhuanxiangTujiBanQuanjieDoocsKaiyuanShequ/img/loader.gif
JianZhiOfferZhuanxiangTujiBanQuanjieDoocsKaiyuanShequ/img/menu-icon.png
JianZhiOfferZhuanxiangTujiBanQuanjieDoocsKaiyuanShequ/img/save.png
JianZhiOfferZhuanxiangTujiBanQuanjieDoocsKaiyuanShequ/img/saved.png
JianZhiOfferZhuanxiangTujiBanQuanjieDoocsKaiyuanShequ/img/settings-s.png
JianZhiOfferZhuanxiangTujiBanQuanjieDoocsKaiyuanShequ/img/settings.png
jian_zhi_offer_zhuanxiang_tuji_ban_quanjie_doocs_kaiyuan_shequ-2024.3.5.0.dist-info/METADATA
jian_zhi_offer_zhuanxiang_tuji_ban_quanjie_doocs_kaiyuan_shequ-2024.3.5.0.dist-info/WHEEL
jian_zhi_offer_zhuanxiang_tuji_ban_quanjie_doocs_kaiyuan_shequ-2024.3.5.0.dist-info/entry_points.txt
jian_zhi_offer_zhuanxiang_tuji_ban_quanjie_doocs_kaiyuan_shequ-2024.3.5.0.dist-info/top_level.txt
jian_zhi_offer_zhuanxiang_tuji_ban_quanjie_doocs_kaiyuan_shequ-2024.3.5.0.dist-info/RECORD
